ysnetconf/__init__.py
ysnetconf/_version.py
ysnetconf/apps.py
ysnetconf/device_plugin.py
ysnetconf/nconf.py
ysnetconf/rpcbuilder.py
ysnetconf/urls.py
ysnetconf/static/ysnetconf/css/netconf.css
ysnetconf/static/ysnetconf/docs/.buildinfo
ysnetconf/static/ysnetconf/docs/environment.pickle
ysnetconf/static/ysnetconf/docs/genindex.fjson
ysnetconf/static/ysnetconf/docs/genindex.html
ysnetconf/static/ysnetconf/docs/globalcontext.json
ysnetconf/static/ysnetconf/docs/index.fjson
ysnetconf/static/ysnetconf/docs/index.html
ysnetconf/static/ysnetconf/docs/last_build
ysnetconf/static/ysnetconf/docs/lock-unlock.fjson
ysnetconf/static/ysnetconf/docs/lock-unlock.html
ysnetconf/static/ysnetconf/docs/notifications.fjson
ysnetconf/static/ysnetconf/docs/notifications.html
ysnetconf/static/ysnetconf/docs/objects.inv
ysnetconf/static/ysnetconf/docs/rpcs.fjson
ysnetconf/static/ysnetconf/docs/rpcs.html
ysnetconf/static/ysnetconf/docs/search.fjson
ysnetconf/static/ysnetconf/docs/search.html
ysnetconf/static/ysnetconf/docs/searchindex.js
ysnetconf/static/ysnetconf/docs/searchindex.json
ysnetconf/static/ysnetconf/docs/tasks.fjson
ysnetconf/static/ysnetconf/docs/tasks.html
ysnetconf/static/ysnetconf/docs/.doctrees/environment.pickle
ysnetconf/static/ysnetconf/docs/.doctrees/index.doctree
ysnetconf/static/ysnetconf/docs/.doctrees/lock-unlock.doctree
ysnetconf/static/ysnetconf/docs/.doctrees/notifications.doctree
ysnetconf/static/ysnetconf/docs/.doctrees/rpcs.doctree
ysnetconf/static/ysnetconf/docs/.doctrees/tasks.doctree
ysnetconf/static/ysnetconf/docs/_images/actions-get-streams.png
ysnetconf/static/ysnetconf/docs/_images/add-var.png
ysnetconf/static/ysnetconf/docs/_images/config-mode.png
ysnetconf/static/ysnetconf/docs/_images/create-task.png
ysnetconf/static/ysnetconf/docs/_images/device-window-no-session.png
ysnetconf/static/ysnetconf/docs/_images/device-window-with-session.png
ysnetconf/static/ysnetconf/docs/_images/get-config-dialog.png
yangsuite_netconf-1.17.27.dist-info/LICENSE.txt
yangsuite_netconf-1.17.27.dist-info/METADATA
yangsuite_netconf-1.17.27.dist-info/WHEEL
yangsuite_netconf-1.17.27.dist-info/entry_points.txt
yangsuite_netconf-1.17.27.dist-info/top_level.txt
yangsuite_netconf-1.17.27.dist-info/RECORD
