Metadata-Version: 2.1
Name: yangsuite-netconf
Version: 1.17.27
Summary: Adds NETCONF protocol (https://tools.ietf.org/html/rfc6241, https://tools.ietf.org/html/rfc7950) support to YANG Suite. Allows the user to build NETCONF RPC messages and execute them on live network devices that support NETCONF. Users can also subscribe to NETCONF event notifications (https://tools.ietf.org/html/rfc5277) from devices with this capability.
Home-page: https://developer.cisco.com
Author: Michael Ott
Author-email: miott@cisco.com
License: Cisco End User License Agreement
Requires-Python: >=3.6
License-File: LICENSE.txt
Requires-Dist: yangsuite >=3.0.0
Requires-Dist: yangsuite-devices >=2.0.0
Requires-Dist: yangsuite-filemanager >=1.5.0
Requires-Dist: yangsuite-yangtree >=2.0.5
